<?xml version="1.0" encoding="UTF-8"?>
<objects serializationModel="Studio.02.02.00">
	<object class="Event" id="{33fcccd9-517e-4a22-a8ce-ff4c0d64331a}">
		<property name="name">
			<value>bombfuse</value>
		</property>
		<property name="outputFormat">
			<value>2</value>
		</property>
		<relationship name="folder">
			<destination>{83c65b71-f23e-442b-ac83-d65fa9323abe}</destination>
		</relationship>
		<relationship name="mixer">
			<destination>{cd294e83-836c-4045-ae09-dca67af89ac8}</destination>
		</relationship>
		<relationship name="masterTrack">
			<destination>{6985dc58-a4c2-4fa2-8a4a-8a2db59e0728}</destination>
		</relationship>
		<relationship name="mixerInput">
			<destination>{c3534050-77be-478a-8bca-d2f9de4639d7}</destination>
		</relationship>
		<relationship name="automatableProperties">
			<destination>{b217c0de-862b-468f-ab98-04c777f18f3b}</destination>
		</relationship>
		<relationship name="markerTracks">
			<destination>{2a59388c-adb2-4958-b821-6995d2454187}</destination>
		</relationship>
		<relationship name="groupTracks">
			<destination>{94e4dcbc-2a3b-465c-9520-5e9ab3f0bcf1}</destination>
		</relationship>
		<relationship name="timeline">
			<destination>{85f0439a-82a0-4713-8ea7-3cb94b9c1079}</destination>
		</relationship>
		<relationship name="banks">
			<destination>{64ada51c-2d91-4a87-a4b8-1997efcb023b}</destination>
		</relationship>
	</object>
	<object class="EventMixer" id="{cd294e83-836c-4045-ae09-dca67af89ac8}">
		<relationship name="masterBus">
			<destination>{b4268d13-a869-4867-9668-b1094a008247}</destination>
		</relationship>
	</object>
	<object class="MasterTrack" id="{6985dc58-a4c2-4fa2-8a4a-8a2db59e0728}">
		<relationship name="mixerGroup">
			<destination>{b4268d13-a869-4867-9668-b1094a008247}</destination>
		</relationship>
	</object>
	<object class="MixerInput" id="{c3534050-77be-478a-8bca-d2f9de4639d7}">
		<relationship name="effectChain">
			<destination>{8d9cc8fb-5fb0-4ea3-8983-dd0bd251c2b4}</destination>
		</relationship>
		<relationship name="panner">
			<destination>{3f69fdab-5ad4-4b74-a480-492f197a15d6}</destination>
		</relationship>
		<relationship name="output">
			<destination>{f18d5877-3d50-41c0-b6c0-9be04ada9938}</destination>
		</relationship>
	</object>
	<object class="EventAutomatableProperties" id="{b217c0de-862b-468f-ab98-04c777f18f3b}">
		<property name="dopplerScale">
			<value>0</value>
		</property>
		<property name="minimumDistance">
			<value>0</value>
		</property>
		<property name="maximumDistance">
			<value>2000</value>
		</property>
	</object>
	<object class="MarkerTrack" id="{2a59388c-adb2-4958-b821-6995d2454187}" />
	<object class="GroupTrack" id="{94e4dcbc-2a3b-465c-9520-5e9ab3f0bcf1}">
		<relationship name="modules">
			<destination>{51015da7-bc8c-4ab4-b0a4-cbd5150f0dfe}</destination>
		</relationship>
		<relationship name="mixerGroup">
			<destination>{e1a2bd70-706c-458e-8844-ac95c9cab251}</destination>
		</relationship>
	</object>
	<object class="Timeline" id="{85f0439a-82a0-4713-8ea7-3cb94b9c1079}">
		<relationship name="modules">
			<destination>{51015da7-bc8c-4ab4-b0a4-cbd5150f0dfe}</destination>
		</relationship>
	</object>
	<object class="EventMixerMaster" id="{b4268d13-a869-4867-9668-b1094a008247}">
		<relationship name="effectChain">
			<destination>{f83fe3d4-e831-4c27-bd0f-becb9e529c9f}</destination>
		</relationship>
		<relationship name="panner">
			<destination>{97d39398-3d9b-4f6e-b0b7-f94295b4e4dc}</destination>
		</relationship>
		<relationship name="mixer">
			<destination>{cd294e83-836c-4045-ae09-dca67af89ac8}</destination>
		</relationship>
	</object>
	<object class="MixerBusEffectChain" id="{8d9cc8fb-5fb0-4ea3-8983-dd0bd251c2b4}">
		<relationship name="effects">
			<destination>{2ad91a32-0cf8-4840-8348-4ce2f538ac9c}</destination>
		</relationship>
	</object>
	<object class="MixerBusPanner" id="{3f69fdab-5ad4-4b74-a480-492f197a15d6}" />
	<object class="SingleSound" id="{51015da7-bc8c-4ab4-b0a4-cbd5150f0dfe}">
		<property name="length">
			<value>13.846125000000001</value>
		</property>
		<relationship name="audioFile">
			<destination>{54161cbd-5053-47ab-b304-142dedf12b17}</destination>
		</relationship>
	</object>
	<object class="EventMixerGroup" id="{e1a2bd70-706c-458e-8844-ac95c9cab251}">
		<property name="volume">
			<value>-24</value>
		</property>
		<property name="name">
			<value>Audio 1</value>
		</property>
		<relationship name="modulators">
			<destination>{c48971e9-f6ff-476f-9282-de4147532553}</destination>
		</relationship>
		<relationship name="effectChain">
			<destination>{34e0e6f6-c5c6-448c-a72d-83093c04a17d}</destination>
		</relationship>
		<relationship name="panner">
			<destination>{5a95f103-ea6c-4ef6-90fe-41959105364f}</destination>
		</relationship>
		<relationship name="output">
			<destination>{b4268d13-a869-4867-9668-b1094a008247}</destination>
		</relationship>
	</object>
	<object class="MixerBusEffectChain" id="{f83fe3d4-e831-4c27-bd0f-becb9e529c9f}">
		<relationship name="effects">
			<destination>{8b508eac-07f7-4f6f-96cf-80c965c5d73b}</destination>
			<destination>{c18cb3bd-3336-4593-86aa-36270b64c70e}</destination>
		</relationship>
	</object>
	<object class="MixerBusPanner" id="{97d39398-3d9b-4f6e-b0b7-f94295b4e4dc}" />
	<object class="MixerBusFader" id="{2ad91a32-0cf8-4840-8348-4ce2f538ac9c}" />
	<object class="ADSRModulator" id="{c48971e9-f6ff-476f-9282-de4147532553}">
		<property name="nameOfPropertyBeingModulated">
			<value>volume</value>
		</property>
		<property name="initialValue">
			<value>-80</value>
		</property>
		<property name="attackTime">
			<value>200</value>
		</property>
		<property name="finalValue">
			<value>-80</value>
		</property>
	</object>
	<object class="MixerBusEffectChain" id="{34e0e6f6-c5c6-448c-a72d-83093c04a17d}">
		<relationship name="effects">
			<destination>{54650981-a1c4-4a75-a4ff-fa75841f07f3}</destination>
		</relationship>
	</object>
	<object class="MixerBusPanner" id="{5a95f103-ea6c-4ef6-90fe-41959105364f}" />
	<object class="MixerBusFader" id="{8b508eac-07f7-4f6f-96cf-80c965c5d73b}" />
	<object class="ProxyEffect" id="{c18cb3bd-3336-4593-86aa-36270b64c70e}">
		<property name="inputFormat">
			<value>1</value>
		</property>
		<relationship name="preset">
			<destination>{544615da-5f6b-4e23-8fe1-24657667d5fd}</destination>
		</relationship>
	</object>
	<object class="MixerBusFader" id="{54650981-a1c4-4a75-a4ff-fa75841f07f3}" />
</objects>
