<?xml version="1.0" encoding="UTF-8"?>
<objects serializationModel="Studio.02.02.00">
	<object class="Event" id="{36bfa083-e22a-4b65-856d-b98266b61959}">
		<property name="name">
			<value>comingoutground</value>
		</property>
		<property name="outputFormat">
			<value>2</value>
		</property>
		<relationship name="folder">
			<destination>{e09846bd-d533-4604-af4a-e78598b25750}</destination>
		</relationship>
		<relationship name="mixer">
			<destination>{a061e187-6c68-48a6-a7c0-337083686162}</destination>
		</relationship>
		<relationship name="masterTrack">
			<destination>{6d00b8e5-e2a5-4da5-bf6f-3c8e169aefd7}</destination>
		</relationship>
		<relationship name="mixerInput">
			<destination>{f48a952a-0826-4625-abf4-c453ff912bc5}</destination>
		</relationship>
		<relationship name="automatableProperties">
			<destination>{f91d1420-1fec-41b3-974f-f75df1005003}</destination>
		</relationship>
		<relationship name="markerTracks">
			<destination>{ed436640-e964-49a6-9c4e-77bf37bc36b0}</destination>
		</relationship>
		<relationship name="groupTracks">
			<destination>{f90affa9-ddcf-4b5b-82fb-2a3e44168696}</destination>
			<destination>{84e61cf4-1e42-46b2-a7a4-58472cbd43e3}</destination>
		</relationship>
		<relationship name="timeline">
			<destination>{5f6e25bc-65ef-4763-8e12-b70551a3cbf5}</destination>
		</relationship>
		<relationship name="banks">
			<destination>{64ada51c-2d91-4a87-a4b8-1997efcb023b}</destination>
		</relationship>
	</object>
	<object class="EventMixer" id="{a061e187-6c68-48a6-a7c0-337083686162}">
		<relationship name="masterBus">
			<destination>{3f073e9e-7bd2-4f05-bb35-a334ad2467b4}</destination>
		</relationship>
	</object>
	<object class="MasterTrack" id="{6d00b8e5-e2a5-4da5-bf6f-3c8e169aefd7}">
		<relationship name="mixerGroup">
			<destination>{3f073e9e-7bd2-4f05-bb35-a334ad2467b4}</destination>
		</relationship>
	</object>
	<object class="MixerInput" id="{f48a952a-0826-4625-abf4-c453ff912bc5}">
		<relationship name="effectChain">
			<destination>{381c01bb-7bd7-42d6-bcde-25044b8fd01e}</destination>
		</relationship>
		<relationship name="panner">
			<destination>{68283996-21df-4bc2-8acc-26a9ac357fba}</destination>
		</relationship>
		<relationship name="output">
			<destination>{f18d5877-3d50-41c0-b6c0-9be04ada9938}</destination>
		</relationship>
	</object>
	<object class="EventAutomatableProperties" id="{f91d1420-1fec-41b3-974f-f75df1005003}">
		<property name="dopplerScale">
			<value>0</value>
		</property>
		<property name="minimumDistance">
			<value>0</value>
		</property>
		<property name="maximumDistance">
			<value>2000</value>
		</property>
	</object>
	<object class="MarkerTrack" id="{ed436640-e964-49a6-9c4e-77bf37bc36b0}" />
	<object class="GroupTrack" id="{f90affa9-ddcf-4b5b-82fb-2a3e44168696}">
		<relationship name="modules">
			<destination>{5ff79337-277a-46dd-895e-30b63e167b8a}</destination>
		</relationship>
		<relationship name="mixerGroup">
			<destination>{bfe6cdd7-fb18-4a17-8985-0c34cf294085}</destination>
		</relationship>
	</object>
	<object class="GroupTrack" id="{84e61cf4-1e42-46b2-a7a4-58472cbd43e3}">
		<relationship name="modules">
			<destination>{bfdcca38-7b4b-4528-bb8d-0ea30b3db718}</destination>
		</relationship>
		<relationship name="mixerGroup">
			<destination>{ac1ed7fb-d4ea-4d04-9aab-5cdf6a333006}</destination>
		</relationship>
	</object>
	<object class="Timeline" id="{5f6e25bc-65ef-4763-8e12-b70551a3cbf5}">
		<relationship name="modules">
			<destination>{5ff79337-277a-46dd-895e-30b63e167b8a}</destination>
			<destination>{bfdcca38-7b4b-4528-bb8d-0ea30b3db718}</destination>
		</relationship>
	</object>
	<object class="EventMixerMaster" id="{3f073e9e-7bd2-4f05-bb35-a334ad2467b4}">
		<relationship name="effectChain">
			<destination>{279b4b04-6f1e-4390-994c-6dcb38bdcc7e}</destination>
		</relationship>
		<relationship name="panner">
			<destination>{fcb747f8-ab71-4323-8650-7beee0c020f1}</destination>
		</relationship>
		<relationship name="mixer">
			<destination>{a061e187-6c68-48a6-a7c0-337083686162}</destination>
		</relationship>
	</object>
	<object class="MixerBusEffectChain" id="{381c01bb-7bd7-42d6-bcde-25044b8fd01e}">
		<relationship name="effects">
			<destination>{78b222ca-05a4-4883-97cf-e61e0c0de838}</destination>
		</relationship>
	</object>
	<object class="MixerBusPanner" id="{68283996-21df-4bc2-8acc-26a9ac357fba}" />
	<object class="SingleSound" id="{5ff79337-277a-46dd-895e-30b63e167b8a}">
		<property name="length">
			<value>0.80000000000000004</value>
		</property>
		<property name="timelockedOffset">
			<value>0.13169863068735771</value>
		</property>
		<property name="pitch">
			<value>-5</value>
		</property>
		<relationship name="audioFile">
			<destination>{e85e7f7c-3b82-49c0-82fc-cbf472965355}</destination>
		</relationship>
	</object>
	<object class="EventMixerGroup" id="{bfe6cdd7-fb18-4a17-8985-0c34cf294085}">
		<property name="volume">
			<value>-9</value>
		</property>
		<property name="name">
			<value>Audio 1</value>
		</property>
		<relationship name="effectChain">
			<destination>{6424d220-b986-4d47-b2f8-6cc0eed6136a}</destination>
		</relationship>
		<relationship name="panner">
			<destination>{869f5ef0-7a01-4bf8-849d-6c484b021d6b}</destination>
		</relationship>
		<relationship name="output">
			<destination>{3f073e9e-7bd2-4f05-bb35-a334ad2467b4}</destination>
		</relationship>
	</object>
	<object class="SingleSound" id="{bfdcca38-7b4b-4528-bb8d-0ea30b3db718}">
		<property name="start">
			<value>0.80000000000000004</value>
		</property>
		<property name="length">
			<value>2.6796441701670242</value>
		</property>
		<property name="timelockedOffset">
			<value>0.07999999999999996</value>
		</property>
		<property name="pitch">
			<value>5</value>
		</property>
		<relationship name="audioFile">
			<destination>{b8899772-3394-44cd-8c76-f7ce2ffd3c87}</destination>
		</relationship>
	</object>
	<object class="EventMixerGroup" id="{ac1ed7fb-d4ea-4d04-9aab-5cdf6a333006}">
		<property name="volume">
			<value>-11.5</value>
		</property>
		<property name="name">
			<value>Audio 2</value>
		</property>
		<relationship name="effectChain">
			<destination>{c4fc3862-ead1-4dc5-b9ae-bce1638dced4}</destination>
		</relationship>
		<relationship name="panner">
			<destination>{bbed9fb4-8d2c-48d1-849b-4b05ef6953a7}</destination>
		</relationship>
		<relationship name="output">
			<destination>{3f073e9e-7bd2-4f05-bb35-a334ad2467b4}</destination>
		</relationship>
	</object>
	<object class="MixerBusEffectChain" id="{279b4b04-6f1e-4390-994c-6dcb38bdcc7e}">
		<relationship name="effects">
			<destination>{8a400c21-3db8-4654-a581-e548b9fd35a3}</destination>
			<destination>{75ee3b4b-38bd-44fd-8654-ff41c7258be4}</destination>
		</relationship>
	</object>
	<object class="MixerBusPanner" id="{fcb747f8-ab71-4323-8650-7beee0c020f1}" />
	<object class="MixerBusFader" id="{78b222ca-05a4-4883-97cf-e61e0c0de838}" />
	<object class="MixerBusEffectChain" id="{6424d220-b986-4d47-b2f8-6cc0eed6136a}">
		<relationship name="effects">
			<destination>{ae01b752-3a2c-496f-bb4b-86f18584fca0}</destination>
			<destination>{443d17e7-08c6-44ee-ab05-4d985e00f86d}</destination>
		</relationship>
	</object>
	<object class="MixerBusPanner" id="{869f5ef0-7a01-4bf8-849d-6c484b021d6b}" />
	<object class="MixerBusEffectChain" id="{c4fc3862-ead1-4dc5-b9ae-bce1638dced4}">
		<relationship name="effects">
			<destination>{55d21b2f-5337-4586-bda3-d408b2d40782}</destination>
		</relationship>
	</object>
	<object class="MixerBusPanner" id="{bbed9fb4-8d2c-48d1-849b-4b05ef6953a7}" />
	<object class="MixerBusFader" id="{8a400c21-3db8-4654-a581-e548b9fd35a3}" />
	<object class="ProxyEffect" id="{75ee3b4b-38bd-44fd-8654-ff41c7258be4}">
		<property name="inputFormat">
			<value>1</value>
		</property>
		<relationship name="preset">
			<destination>{544615da-5f6b-4e23-8fe1-24657667d5fd}</destination>
		</relationship>
	</object>
	<object class="MixerBusFader" id="{ae01b752-3a2c-496f-bb4b-86f18584fca0}" />
	<object class="ThreeEQEffect" id="{443d17e7-08c6-44ee-ab05-4d985e00f86d}">
		<property name="midGain">
			<value>-6</value>
		</property>
	</object>
	<object class="MixerBusFader" id="{55d21b2f-5337-4586-bda3-d408b2d40782}" />
</objects>
