<?xml version="1.0" encoding="UTF-8"?>
<objects serializationModel="Studio.02.02.00">
	<object class="Event" id="{7a989a42-4c02-4223-95d2-78c81e2fde07}">
		<property name="note">
			<value>inaccurate</value>
		</property>
		<property name="name">
			<value>mortslap</value>
		</property>
		<property name="outputFormat">
			<value>2</value>
		</property>
		<relationship name="folder">
			<destination>{7a2507ec-d1d4-4e41-9164-f19d5d2939ae}</destination>
		</relationship>
		<relationship name="mixer">
			<destination>{8bc7f561-35cf-487b-bf2e-629857619978}</destination>
		</relationship>
		<relationship name="masterTrack">
			<destination>{dd4fc00d-0b3e-4cdb-b75c-3d540b5e1b5f}</destination>
		</relationship>
		<relationship name="mixerInput">
			<destination>{e89221ae-0e49-4be2-94b4-7b6e9e66dba8}</destination>
		</relationship>
		<relationship name="automatableProperties">
			<destination>{2301b778-60f5-40bd-9634-a4652c2851d2}</destination>
		</relationship>
		<relationship name="markerTracks">
			<destination>{8cc6eb49-ae89-4b0f-8e55-2625178f85db}</destination>
		</relationship>
		<relationship name="groupTracks">
			<destination>{890715a8-38f1-4fbd-af15-7b11e770e32a}</destination>
		</relationship>
		<relationship name="timeline">
			<destination>{13dce628-e33e-432b-ad16-7fbcb24b8997}</destination>
		</relationship>
		<relationship name="banks">
			<destination>{64ada51c-2d91-4a87-a4b8-1997efcb023b}</destination>
		</relationship>
	</object>
	<object class="EventMixer" id="{8bc7f561-35cf-487b-bf2e-629857619978}">
		<relationship name="masterBus">
			<destination>{f03bd209-3919-4e4b-b29b-d4ea54d31ca1}</destination>
		</relationship>
	</object>
	<object class="MasterTrack" id="{dd4fc00d-0b3e-4cdb-b75c-3d540b5e1b5f}">
		<relationship name="mixerGroup">
			<destination>{f03bd209-3919-4e4b-b29b-d4ea54d31ca1}</destination>
		</relationship>
	</object>
	<object class="MixerInput" id="{e89221ae-0e49-4be2-94b4-7b6e9e66dba8}">
		<relationship name="effectChain">
			<destination>{784e9b4a-6590-4c1b-9bde-6002345487f1}</destination>
		</relationship>
		<relationship name="panner">
			<destination>{0a181484-4af1-400b-a427-b25131e0218a}</destination>
		</relationship>
		<relationship name="output">
			<destination>{f18d5877-3d50-41c0-b6c0-9be04ada9938}</destination>
		</relationship>
	</object>
	<object class="EventAutomatableProperties" id="{2301b778-60f5-40bd-9634-a4652c2851d2}">
		<property name="dopplerScale">
			<value>0</value>
		</property>
		<property name="minimumDistance">
			<value>0</value>
		</property>
		<property name="maximumDistance">
			<value>2000</value>
		</property>
	</object>
	<object class="MarkerTrack" id="{8cc6eb49-ae89-4b0f-8e55-2625178f85db}" />
	<object class="GroupTrack" id="{890715a8-38f1-4fbd-af15-7b11e770e32a}">
		<relationship name="modules">
			<destination>{033d50ca-ddc6-4fc9-a7cf-2d8c35d6b683}</destination>
		</relationship>
		<relationship name="mixerGroup">
			<destination>{1297a051-dbf8-4301-85f8-deeed4c6c343}</destination>
		</relationship>
	</object>
	<object class="Timeline" id="{13dce628-e33e-432b-ad16-7fbcb24b8997}">
		<relationship name="modules">
			<destination>{033d50ca-ddc6-4fc9-a7cf-2d8c35d6b683}</destination>
		</relationship>
	</object>
	<object class="EventMixerMaster" id="{f03bd209-3919-4e4b-b29b-d4ea54d31ca1}">
		<relationship name="effectChain">
			<destination>{35a0bf1d-d0b9-4cdf-9207-06c90a28524a}</destination>
		</relationship>
		<relationship name="panner">
			<destination>{9639564b-2bcb-468b-a563-48ca0b6b3e8a}</destination>
		</relationship>
		<relationship name="mixer">
			<destination>{8bc7f561-35cf-487b-bf2e-629857619978}</destination>
		</relationship>
	</object>
	<object class="MixerBusEffectChain" id="{784e9b4a-6590-4c1b-9bde-6002345487f1}">
		<relationship name="effects">
			<destination>{3a199801-4679-41c4-8606-a45d84dc74ae}</destination>
		</relationship>
	</object>
	<object class="MixerBusPanner" id="{0a181484-4af1-400b-a427-b25131e0218a}" />
	<object class="SingleSound" id="{033d50ca-ddc6-4fc9-a7cf-2d8c35d6b683}">
		<property name="length">
			<value>0.47524999999999995</value>
		</property>
		<property name="timelockedOffset">
			<value>0.13</value>
		</property>
		<relationship name="audioFile">
			<destination>{c0cc7768-1868-4ab6-bfa8-7d327290fe83}</destination>
		</relationship>
	</object>
	<object class="EventMixerGroup" id="{1297a051-dbf8-4301-85f8-deeed4c6c343}">
		<property name="volume">
			<value>-6</value>
		</property>
		<property name="name">
			<value>Audio 1</value>
		</property>
		<relationship name="effectChain">
			<destination>{064c0f4c-41d2-4942-9103-1a10b8a01d50}</destination>
		</relationship>
		<relationship name="panner">
			<destination>{ba0ee5be-a87f-4a5b-a73c-d0ad665ac217}</destination>
		</relationship>
		<relationship name="output">
			<destination>{f03bd209-3919-4e4b-b29b-d4ea54d31ca1}</destination>
		</relationship>
	</object>
	<object class="MixerBusEffectChain" id="{35a0bf1d-d0b9-4cdf-9207-06c90a28524a}">
		<relationship name="effects">
			<destination>{76c8ac9e-6d36-4156-bc24-363f0861561f}</destination>
			<destination>{f331cf3c-166b-434f-8247-0135b1c38f49}</destination>
		</relationship>
	</object>
	<object class="MixerBusPanner" id="{9639564b-2bcb-468b-a563-48ca0b6b3e8a}" />
	<object class="MixerBusFader" id="{3a199801-4679-41c4-8606-a45d84dc74ae}" />
	<object class="MixerBusEffectChain" id="{064c0f4c-41d2-4942-9103-1a10b8a01d50}">
		<relationship name="effects">
			<destination>{5b28fac7-0ca1-4988-9769-ba27262360be}</destination>
		</relationship>
	</object>
	<object class="MixerBusPanner" id="{ba0ee5be-a87f-4a5b-a73c-d0ad665ac217}" />
	<object class="MixerBusFader" id="{76c8ac9e-6d36-4156-bc24-363f0861561f}" />
	<object class="ProxyEffect" id="{f331cf3c-166b-434f-8247-0135b1c38f49}">
		<property name="inputFormat">
			<value>1</value>
		</property>
		<relationship name="preset">
			<destination>{544615da-5f6b-4e23-8fe1-24657667d5fd}</destination>
		</relationship>
	</object>
	<object class="MixerBusFader" id="{5b28fac7-0ca1-4988-9769-ba27262360be}" />
</objects>
