<?xml version="1.0" encoding="UTF-8"?>
<objects serializationModel="Studio.02.02.00">
	<object class="Event" id="{85155b0c-7c62-4532-9db8-410ff6af3862}">
		<property name="name">
			<value>finaljudgement_start</value>
		</property>
		<property name="outputFormat">
			<value>0</value>
		</property>
		<relationship name="folder">
			<destination>{48fdf35b-4165-4100-8117-4f9b71366dc0}</destination>
		</relationship>
		<relationship name="mixer">
			<destination>{0bcfdef0-b779-4f7d-a8ba-35090eafea3a}</destination>
		</relationship>
		<relationship name="masterTrack">
			<destination>{73e640d3-2a23-40a4-8271-827961a0a89f}</destination>
		</relationship>
		<relationship name="mixerInput">
			<destination>{f37289e7-5f0f-4923-89f6-633947e702ad}</destination>
		</relationship>
		<relationship name="automatableProperties">
			<destination>{f2732070-d0b6-4279-b3c7-3226689bfb5d}</destination>
		</relationship>
		<relationship name="markerTracks">
			<destination>{bfc4416d-0dea-42e7-b6a2-03cfedd57d22}</destination>
		</relationship>
		<relationship name="groupTracks">
			<destination>{c0bc4a5d-dc6a-4491-9da2-91e0be30fcb0}</destination>
		</relationship>
		<relationship name="timeline">
			<destination>{09823e5b-f847-49f2-b14b-4fe0fa6f74b9}</destination>
		</relationship>
		<relationship name="banks">
			<destination>{64ada51c-2d91-4a87-a4b8-1997efcb023b}</destination>
		</relationship>
	</object>
	<object class="EventMixer" id="{0bcfdef0-b779-4f7d-a8ba-35090eafea3a}">
		<relationship name="masterBus">
			<destination>{1399010e-23fb-4e49-803d-0fd0e3ecb3d2}</destination>
		</relationship>
	</object>
	<object class="MasterTrack" id="{73e640d3-2a23-40a4-8271-827961a0a89f}">
		<relationship name="modules">
			<destination>{7f99f5db-994e-4b48-9809-97ecca70a2ff}</destination>
			<destination>{da15f105-1c58-44b7-8c03-2e8b18c9de52}</destination>
		</relationship>
		<relationship name="mixerGroup">
			<destination>{1399010e-23fb-4e49-803d-0fd0e3ecb3d2}</destination>
		</relationship>
	</object>
	<object class="MixerInput" id="{f37289e7-5f0f-4923-89f6-633947e702ad}">
		<relationship name="effectChain">
			<destination>{17b53aed-b619-4666-acf4-8fdd3a5333fd}</destination>
		</relationship>
		<relationship name="panner">
			<destination>{443e9032-03aa-47cd-b704-74f4191aca15}</destination>
		</relationship>
		<relationship name="output">
			<destination>{f18d5877-3d50-41c0-b6c0-9be04ada9938}</destination>
		</relationship>
	</object>
	<object class="EventAutomatableProperties" id="{f2732070-d0b6-4279-b3c7-3226689bfb5d}">
		<property name="dopplerScale">
			<value>0</value>
		</property>
		<property name="minimumDistance">
			<value>0</value>
		</property>
		<property name="maximumDistance">
			<value>2000</value>
		</property>
	</object>
	<object class="MarkerTrack" id="{bfc4416d-0dea-42e7-b6a2-03cfedd57d22}" />
	<object class="GroupTrack" id="{c0bc4a5d-dc6a-4491-9da2-91e0be30fcb0}">
		<relationship name="modules">
			<destination>{d100cf44-4f20-4f48-9c03-bb7ea0030c41}</destination>
			<destination>{6bbef0e3-401d-4e57-8879-c8fd9378423a}</destination>
			<destination>{c0cbb697-7bbf-433e-befe-d141e8460764}</destination>
		</relationship>
		<relationship name="mixerGroup">
			<destination>{bb918d88-de04-4b2c-96aa-3035f43ee6df}</destination>
		</relationship>
	</object>
	<object class="Timeline" id="{09823e5b-f847-49f2-b14b-4fe0fa6f74b9}">
		<relationship name="modules">
			<destination>{d100cf44-4f20-4f48-9c03-bb7ea0030c41}</destination>
		</relationship>
		<relationship name="markers">
			<destination>{cba9b3e7-095c-4141-b9a4-52028eef5065}</destination>
		</relationship>
	</object>
	<object class="EventMixerMaster" id="{1399010e-23fb-4e49-803d-0fd0e3ecb3d2}">
		<relationship name="effectChain">
			<destination>{e2be4e1a-aa4a-4c76-a1c5-b5c3b3c09384}</destination>
		</relationship>
		<relationship name="panner">
			<destination>{49ebc8bc-4f70-48a7-a94a-8206520fddb2}</destination>
		</relationship>
		<relationship name="mixer">
			<destination>{0bcfdef0-b779-4f7d-a8ba-35090eafea3a}</destination>
		</relationship>
	</object>
	<object class="TransitionSourceSound" id="{7f99f5db-994e-4b48-9809-97ecca70a2ff}">
		<property name="length">
			<value>0</value>
		</property>
	</object>
	<object class="TransitionDestinationSound" id="{da15f105-1c58-44b7-8c03-2e8b18c9de52}">
		<property name="start">
			<value>0.5</value>
		</property>
		<property name="length">
			<value>0</value>
		</property>
	</object>
	<object class="MixerBusEffectChain" id="{17b53aed-b619-4666-acf4-8fdd3a5333fd}">
		<relationship name="effects">
			<destination>{6c7bbd20-21b2-402e-848f-0c11679db0b0}</destination>
		</relationship>
	</object>
	<object class="MixerBusPanner" id="{443e9032-03aa-47cd-b704-74f4191aca15}" />
	<object class="SingleSound" id="{d100cf44-4f20-4f48-9c03-bb7ea0030c41}">
		<property name="length">
			<value>7.9375</value>
		</property>
		<relationship name="audioFile">
			<destination>{81a1906d-d66b-4ca8-a470-13a6ede8ff58}</destination>
		</relationship>
	</object>
	<object class="TransitionSourceSound" id="{6bbef0e3-401d-4e57-8879-c8fd9378423a}">
		<property name="length">
			<value>0.5</value>
		</property>
		<relationship name="fadeOutCurve">
			<destination>{f05360c3-6465-424d-8de8-6baa0fea4aa2}</destination>
		</relationship>
	</object>
	<object class="TransitionDestinationSound" id="{c0cbb697-7bbf-433e-befe-d141e8460764}">
		<property name="length">
			<value>0.5</value>
		</property>
		<relationship name="fadeInCurve">
			<destination>{d83a0d12-18ff-4883-99ae-b3a593a6e628}</destination>
		</relationship>
	</object>
	<object class="EventMixerGroup" id="{bb918d88-de04-4b2c-96aa-3035f43ee6df}">
		<property name="name">
			<value>Audio 1</value>
		</property>
		<relationship name="modulators">
			<destination>{4442eb15-9791-47b2-ad7d-95cc384a5a02}</destination>
		</relationship>
		<relationship name="effectChain">
			<destination>{3ae012d3-40a7-4b1b-a8f2-664f3ace4dc4}</destination>
		</relationship>
		<relationship name="panner">
			<destination>{4158783b-75fa-4b0e-a000-28beea27b57f}</destination>
		</relationship>
		<relationship name="output">
			<destination>{1399010e-23fb-4e49-803d-0fd0e3ecb3d2}</destination>
		</relationship>
	</object>
	<object class="LoopRegion" id="{cba9b3e7-095c-4141-b9a4-52028eef5065}">
		<property name="position">
			<value>0.40000000000000002</value>
		</property>
		<property name="length">
			<value>4.5</value>
		</property>
		<relationship name="timeline">
			<destination>{09823e5b-f847-49f2-b14b-4fe0fa6f74b9}</destination>
		</relationship>
		<relationship name="markerTrack">
			<destination>{bfc4416d-0dea-42e7-b6a2-03cfedd57d22}</destination>
		</relationship>
		<relationship name="transitionTimeline">
			<destination>{b6cc68ca-c4c6-44d5-9ace-2c7fccffce4b}</destination>
		</relationship>
	</object>
	<object class="MixerBusEffectChain" id="{e2be4e1a-aa4a-4c76-a1c5-b5c3b3c09384}">
		<relationship name="effects">
			<destination>{d8100345-cc4e-4494-8215-a9b8aa39da25}</destination>
		</relationship>
	</object>
	<object class="MixerBusPanner" id="{49ebc8bc-4f70-48a7-a94a-8206520fddb2}" />
	<object class="MixerBusFader" id="{6c7bbd20-21b2-402e-848f-0c11679db0b0}" />
	<object class="TransitionSourceFadeOutCurve" id="{f05360c3-6465-424d-8de8-6baa0fea4aa2}">
		<relationship name="startPoint">
			<destination>{10383dbc-c216-4b16-8d83-1179ce6501b4}</destination>
		</relationship>
		<relationship name="endPoint">
			<destination>{cff022e1-faa6-4a4b-8b43-0d50e63c3ab1}</destination>
		</relationship>
		<relationship name="relatedModule">
			<destination>{c0cbb697-7bbf-433e-befe-d141e8460764}</destination>
		</relationship>
	</object>
	<object class="TransitionDestinationFadeInCurve" id="{d83a0d12-18ff-4883-99ae-b3a593a6e628}">
		<relationship name="startPoint">
			<destination>{2a4f7b26-ca52-4d0f-b05d-18594ab21454}</destination>
		</relationship>
		<relationship name="endPoint">
			<destination>{f73f5275-af79-41f4-9e10-854e9344f8a3}</destination>
		</relationship>
		<relationship name="relatedModule">
			<destination>{6bbef0e3-401d-4e57-8879-c8fd9378423a}</destination>
		</relationship>
	</object>
	<object class="ADSRModulator" id="{4442eb15-9791-47b2-ad7d-95cc384a5a02}">
		<property name="nameOfPropertyBeingModulated">
			<value>volume</value>
		</property>
		<property name="initialValue">
			<value>-80</value>
		</property>
		<property name="attackTime">
			<value>0</value>
		</property>
		<property name="releaseTime">
			<value>2000</value>
		</property>
		<property name="finalValue">
			<value>-80</value>
		</property>
	</object>
	<object class="MixerBusEffectChain" id="{3ae012d3-40a7-4b1b-a8f2-664f3ace4dc4}">
		<relationship name="effects">
			<destination>{2be7c98f-5527-4f63-b71d-59198f5ca478}</destination>
		</relationship>
	</object>
	<object class="MixerBusPanner" id="{4158783b-75fa-4b0e-a000-28beea27b57f}" />
	<object class="TransitionTimeline" id="{b6cc68ca-c4c6-44d5-9ace-2c7fccffce4b}">
		<property name="length">
			<value>0.5</value>
		</property>
		<relationship name="modules">
			<destination>{6bbef0e3-401d-4e57-8879-c8fd9378423a}</destination>
			<destination>{c0cbb697-7bbf-433e-befe-d141e8460764}</destination>
			<destination>{7f99f5db-994e-4b48-9809-97ecca70a2ff}</destination>
			<destination>{da15f105-1c58-44b7-8c03-2e8b18c9de52}</destination>
		</relationship>
	</object>
	<object class="MixerBusFader" id="{d8100345-cc4e-4494-8215-a9b8aa39da25}" />
	<object class="AutomationPoint" id="{10383dbc-c216-4b16-8d83-1179ce6501b4}">
		<property name="position">
			<value>0</value>
		</property>
		<property name="value">
			<value>1</value>
		</property>
		<property name="curveShape">
			<value>0.25471893</value>
		</property>
	</object>
	<object class="AutomationPoint" id="{cff022e1-faa6-4a4b-8b43-0d50e63c3ab1}">
		<property name="position">
			<value>0.5</value>
		</property>
		<property name="value">
			<value>0</value>
		</property>
	</object>
	<object class="AutomationPoint" id="{2a4f7b26-ca52-4d0f-b05d-18594ab21454}">
		<property name="position">
			<value>0</value>
		</property>
		<property name="value">
			<value>0</value>
		</property>
		<property name="curveShape">
			<value>-0.2547189</value>
		</property>
	</object>
	<object class="AutomationPoint" id="{f73f5275-af79-41f4-9e10-854e9344f8a3}">
		<property name="position">
			<value>0.5</value>
		</property>
		<property name="value">
			<value>1</value>
		</property>
	</object>
	<object class="MixerBusFader" id="{2be7c98f-5527-4f63-b71d-59198f5ca478}" />
</objects>
