<?xml version="1.0" encoding="UTF-8"?>
<objects serializationModel="Studio.02.02.00">
	<object class="Event" id="{c83933e5-6c81-4cdf-9e0c-c213e687e8fd}">
		<property name="name">
			<value>editor</value>
		</property>
		<property name="outputFormat">
			<value>1</value>
		</property>
		<relationship name="folder">
			<destination>{756a4588-1d1d-435d-9f82-e10a23a30a80}</destination>
		</relationship>
		<relationship name="mixer">
			<destination>{89e84721-1754-4c42-9bdd-24cfacc765b1}</destination>
		</relationship>
		<relationship name="masterTrack">
			<destination>{05fc9054-ae68-4a8c-aaa9-962c697d65a9}</destination>
		</relationship>
		<relationship name="mixerInput">
			<destination>{0daa3c0f-45be-4e0e-ae84-b84d17445965}</destination>
		</relationship>
		<relationship name="automatableProperties">
			<destination>{7461b343-8d46-4b55-b2a3-3807d1471fd1}</destination>
		</relationship>
		<relationship name="markerTracks">
			<destination>{f1968974-529f-4589-8711-47436db40eb2}</destination>
		</relationship>
		<relationship name="groupTracks">
			<destination>{a243b08c-058d-4f89-b4dc-9fb7d878e8cf}</destination>
		</relationship>
		<relationship name="timeline">
			<destination>{46119af6-00e9-4376-80cd-18e761f6ee40}</destination>
		</relationship>
		<relationship name="banks">
			<destination>{d1922f23-f05c-4f1e-bf51-00d19c55549b}</destination>
		</relationship>
	</object>
	<object class="EventMixer" id="{89e84721-1754-4c42-9bdd-24cfacc765b1}">
		<relationship name="masterBus">
			<destination>{e014d53e-5ef9-40b5-9b3f-7f7d8717747b}</destination>
		</relationship>
	</object>
	<object class="MasterTrack" id="{05fc9054-ae68-4a8c-aaa9-962c697d65a9}">
		<relationship name="mixerGroup">
			<destination>{e014d53e-5ef9-40b5-9b3f-7f7d8717747b}</destination>
		</relationship>
	</object>
	<object class="MixerInput" id="{0daa3c0f-45be-4e0e-ae84-b84d17445965}">
		<relationship name="effectChain">
			<destination>{783c7751-313b-4aa8-9d6e-593630722c37}</destination>
		</relationship>
		<relationship name="panner">
			<destination>{4fa46646-1a0c-4a3e-acac-db2e9865c6e9}</destination>
		</relationship>
		<relationship name="output">
			<destination>{032f56ee-6215-4738-8d0b-f630b5c73daf}</destination>
		</relationship>
	</object>
	<object class="EventAutomatableProperties" id="{7461b343-8d46-4b55-b2a3-3807d1471fd1}">
		<property name="priority">
			<value>4</value>
		</property>
	</object>
	<object class="MarkerTrack" id="{f1968974-529f-4589-8711-47436db40eb2}" />
	<object class="GroupTrack" id="{a243b08c-058d-4f89-b4dc-9fb7d878e8cf}">
		<relationship name="modules">
			<destination>{e5c8055d-9e0a-411c-8a2d-018ebd38fb8a}</destination>
		</relationship>
		<relationship name="mixerGroup">
			<destination>{b8a4df53-d10a-4137-8258-0228f4ee926f}</destination>
		</relationship>
	</object>
	<object class="Timeline" id="{46119af6-00e9-4376-80cd-18e761f6ee40}">
		<relationship name="modules">
			<destination>{e5c8055d-9e0a-411c-8a2d-018ebd38fb8a}</destination>
		</relationship>
		<relationship name="markers">
			<destination>{8ba06d4c-aa9e-454b-85cf-7be60ca3e2f1}</destination>
		</relationship>
	</object>
	<object class="EventMixerMaster" id="{e014d53e-5ef9-40b5-9b3f-7f7d8717747b}">
		<relationship name="effectChain">
			<destination>{26b06396-a854-4a65-9539-1666e7a7c6fb}</destination>
		</relationship>
		<relationship name="panner">
			<destination>{74258ff7-853b-437c-b80e-ffb406cb6f1c}</destination>
		</relationship>
		<relationship name="mixer">
			<destination>{89e84721-1754-4c42-9bdd-24cfacc765b1}</destination>
		</relationship>
	</object>
	<object class="MixerBusEffectChain" id="{783c7751-313b-4aa8-9d6e-593630722c37}">
		<relationship name="effects">
			<destination>{0414a1c3-3d4a-4e35-9d7b-37b0ac4159e2}</destination>
		</relationship>
	</object>
	<object class="MixerBusPanner" id="{4fa46646-1a0c-4a3e-acac-db2e9865c6e9}" />
	<object class="SingleSound" id="{e5c8055d-9e0a-411c-8a2d-018ebd38fb8a}">
		<property name="length">
			<value>128.00610416666666</value>
		</property>
		<property name="timelockedOffset">
			<value>0.02</value>
		</property>
		<relationship name="audioFile">
			<destination>{f49dd9fb-7c31-4d38-ac64-5f1fb7c08ae6}</destination>
		</relationship>
	</object>
	<object class="EventMixerGroup" id="{b8a4df53-d10a-4137-8258-0228f4ee926f}">
		<property name="volume">
			<value>6</value>
		</property>
		<property name="name">
			<value>Audio 1</value>
		</property>
		<relationship name="effectChain">
			<destination>{900d01d7-0375-40bb-aa75-775280855c7e}</destination>
		</relationship>
		<relationship name="panner">
			<destination>{b015d196-4ed9-47de-96a4-b8111e2640bc}</destination>
		</relationship>
		<relationship name="output">
			<destination>{e014d53e-5ef9-40b5-9b3f-7f7d8717747b}</destination>
		</relationship>
	</object>
	<object class="LoopRegion" id="{8ba06d4c-aa9e-454b-85cf-7be60ca3e2f1}">
		<property name="position">
			<value>0</value>
		</property>
		<property name="length">
			<value>128.00610416666666</value>
		</property>
		<relationship name="timeline">
			<destination>{46119af6-00e9-4376-80cd-18e761f6ee40}</destination>
		</relationship>
		<relationship name="markerTrack">
			<destination>{f1968974-529f-4589-8711-47436db40eb2}</destination>
		</relationship>
	</object>
	<object class="MixerBusEffectChain" id="{26b06396-a854-4a65-9539-1666e7a7c6fb}">
		<relationship name="effects">
			<destination>{6b8bfcd9-e7a8-42f5-85cc-2a366e20996b}</destination>
		</relationship>
	</object>
	<object class="MixerBusPanner" id="{74258ff7-853b-437c-b80e-ffb406cb6f1c}" />
	<object class="MixerBusFader" id="{0414a1c3-3d4a-4e35-9d7b-37b0ac4159e2}" />
	<object class="MixerBusEffectChain" id="{900d01d7-0375-40bb-aa75-775280855c7e}">
		<relationship name="effects">
			<destination>{97494c15-1c99-48c5-91d5-5e3c51ea56de}</destination>
		</relationship>
	</object>
	<object class="MixerBusPanner" id="{b015d196-4ed9-47de-96a4-b8111e2640bc}" />
	<object class="MixerBusFader" id="{6b8bfcd9-e7a8-42f5-85cc-2a366e20996b}" />
	<object class="MixerBusFader" id="{97494c15-1c99-48c5-91d5-5e3c51ea56de}" />
</objects>
