<?xml version="1.0" encoding="UTF-8"?>
<objects serializationModel="Studio.02.02.00">
	<object class="Event" id="{cf88a17b-5165-481f-af37-9cae73903f25}">
		<property name="name">
			<value>S05 secretdesert</value>
		</property>
		<property name="outputFormat">
			<value>1</value>
		</property>
		<relationship name="folder">
			<destination>{df67a827-3f8a-48c6-87fb-3f41d942e4b2}</destination>
		</relationship>
		<relationship name="mixer">
			<destination>{76cd28c4-a4d1-46cb-800f-55a4720df76a}</destination>
		</relationship>
		<relationship name="masterTrack">
			<destination>{90e39dbd-c50b-429e-a1c7-9e7c05380e88}</destination>
		</relationship>
		<relationship name="mixerInput">
			<destination>{12791e55-3414-4fb9-bc8b-12ff6c19b4df}</destination>
		</relationship>
		<relationship name="automatableProperties">
			<destination>{bf1cb3da-e36a-425c-80f3-ce562a9094e3}</destination>
		</relationship>
		<relationship name="markerTracks">
			<destination>{60521460-3664-443f-a2ff-0b15922df7b3}</destination>
		</relationship>
		<relationship name="groupTracks">
			<destination>{5eb08ddd-6702-48c3-b482-1db8ba08cc4d}</destination>
		</relationship>
		<relationship name="timeline">
			<destination>{9fca7a04-7fcd-457e-a382-1d8d237bd900}</destination>
		</relationship>
		<relationship name="userProperties">
			<destination>{e727f54b-8a02-4031-9b95-761c44b7fa57}</destination>
			<destination>{258abc17-ae4a-46f5-85cc-782ab95f0398}</destination>
			<destination>{4f3cfbcf-0365-4a74-a4d1-0624780e25c8}</destination>
			<destination>{59130b84-1ae7-46b0-a03e-6b9ff172aaed}</destination>
			<destination>{defc07de-445a-47fc-92e1-f3402a15b6d6}</destination>
		</relationship>
		<relationship name="banks">
			<destination>{d1922f23-f05c-4f1e-bf51-00d19c55549b}</destination>
		</relationship>
	</object>
	<object class="EventMixer" id="{76cd28c4-a4d1-46cb-800f-55a4720df76a}">
		<relationship name="masterBus">
			<destination>{6cf48ec9-98fd-4367-ab73-5033a410a87a}</destination>
		</relationship>
	</object>
	<object class="MasterTrack" id="{90e39dbd-c50b-429e-a1c7-9e7c05380e88}">
		<relationship name="mixerGroup">
			<destination>{6cf48ec9-98fd-4367-ab73-5033a410a87a}</destination>
		</relationship>
	</object>
	<object class="MixerInput" id="{12791e55-3414-4fb9-bc8b-12ff6c19b4df}">
		<relationship name="effectChain">
			<destination>{77ac22dd-4024-4990-9209-7435b47cf766}</destination>
		</relationship>
		<relationship name="panner">
			<destination>{15e47e91-1f98-4338-b536-f4ed2fb78fe4}</destination>
		</relationship>
		<relationship name="output">
			<destination>{bd647f4a-9ed4-457f-9d69-57dc03124064}</destination>
		</relationship>
	</object>
	<object class="EventAutomatableProperties" id="{bf1cb3da-e36a-425c-80f3-ce562a9094e3}">
		<property name="priority">
			<value>4</value>
		</property>
	</object>
	<object class="MarkerTrack" id="{60521460-3664-443f-a2ff-0b15922df7b3}" />
	<object class="GroupTrack" id="{5eb08ddd-6702-48c3-b482-1db8ba08cc4d}">
		<relationship name="modules">
			<destination>{25402b6f-41b8-48f4-ba71-3cadd2e704de}</destination>
		</relationship>
		<relationship name="mixerGroup">
			<destination>{7ec65f80-e209-4d86-b1b0-5e841c250b3b}</destination>
		</relationship>
	</object>
	<object class="Timeline" id="{9fca7a04-7fcd-457e-a382-1d8d237bd900}">
		<relationship name="modules">
			<destination>{25402b6f-41b8-48f4-ba71-3cadd2e704de}</destination>
		</relationship>
		<relationship name="markers">
			<destination>{c52a3827-4dc5-4b0d-8ba8-ca9141cc35c9}</destination>
		</relationship>
	</object>
	<object class="UserProperty" id="{e727f54b-8a02-4031-9b95-761c44b7fa57}">
		<property name="key">
			<value>name</value>
		</property>
		<property name="value">
			<value>A Grain of Bread in a Grain of Sand</value>
		</property>
	</object>
	<object class="UserProperty" id="{258abc17-ae4a-46f5-85cc-782ab95f0398}">
		<property name="key">
			<value>author</value>
		</property>
		<property name="value">
			<value>ClascyJitto</value>
		</property>
	</object>
	<object class="UserProperty" id="{4f3cfbcf-0365-4a74-a4d1-0624780e25c8}">
		<property name="key">
			<value>game</value>
		</property>
		<property name="value">
			<value>Pizza Tower</value>
		</property>
	</object>
	<object class="UserProperty" id="{59130b84-1ae7-46b0-a03e-6b9ff172aaed}">
		<property name="key">
			<value>order</value>
		</property>
		<property name="value">
			<value>62</value>
		</property>
	</object>
	<object class="UserProperty" id="{defc07de-445a-47fc-92e1-f3402a15b6d6}">
		<property name="key">
			<value>alt</value>
		</property>
		<property name="value">
			<value>0</value>
		</property>
	</object>
	<object class="EventMixerMaster" id="{6cf48ec9-98fd-4367-ab73-5033a410a87a}">
		<relationship name="effectChain">
			<destination>{f77aaef0-f26e-437f-8c24-df6b984e527c}</destination>
		</relationship>
		<relationship name="panner">
			<destination>{8080646d-16b8-4e7b-83ce-59c7642595ee}</destination>
		</relationship>
		<relationship name="mixer">
			<destination>{76cd28c4-a4d1-46cb-800f-55a4720df76a}</destination>
		</relationship>
	</object>
	<object class="MixerBusEffectChain" id="{77ac22dd-4024-4990-9209-7435b47cf766}">
		<relationship name="effects">
			<destination>{33d13533-5e94-4020-b5f0-f1fa0a636455}</destination>
		</relationship>
	</object>
	<object class="MixerBusPanner" id="{15e47e91-1f98-4338-b536-f4ed2fb78fe4}" />
	<object class="SingleSound" id="{25402b6f-41b8-48f4-ba71-3cadd2e704de}">
		<property name="length">
			<value>71.489354166666672</value>
		</property>
		<relationship name="audioFile">
			<destination>{65273ecd-0ed9-4ea2-b15e-a62bfb267474}</destination>
		</relationship>
	</object>
	<object class="EventMixerGroup" id="{7ec65f80-e209-4d86-b1b0-5e841c250b3b}">
		<property name="volume">
			<value>3</value>
		</property>
		<property name="name">
			<value>Audio 1</value>
		</property>
		<relationship name="effectChain">
			<destination>{3bb15dd7-2f60-4004-9f41-47465c0fe375}</destination>
		</relationship>
		<relationship name="panner">
			<destination>{3e908683-9dc0-48b8-a0f2-7113d4a4a294}</destination>
		</relationship>
		<relationship name="output">
			<destination>{6cf48ec9-98fd-4367-ab73-5033a410a87a}</destination>
		</relationship>
	</object>
	<object class="LoopRegion" id="{c52a3827-4dc5-4b0d-8ba8-ca9141cc35c9}">
		<property name="position">
			<value>0</value>
		</property>
		<property name="length">
			<value>71.489354166666672</value>
		</property>
		<relationship name="timeline">
			<destination>{9fca7a04-7fcd-457e-a382-1d8d237bd900}</destination>
		</relationship>
		<relationship name="markerTrack">
			<destination>{60521460-3664-443f-a2ff-0b15922df7b3}</destination>
		</relationship>
	</object>
	<object class="MixerBusEffectChain" id="{f77aaef0-f26e-437f-8c24-df6b984e527c}">
		<relationship name="effects">
			<destination>{1f656114-c8eb-4194-a9f7-6b1428424cdc}</destination>
		</relationship>
	</object>
	<object class="MixerBusPanner" id="{8080646d-16b8-4e7b-83ce-59c7642595ee}" />
	<object class="MixerBusFader" id="{33d13533-5e94-4020-b5f0-f1fa0a636455}" />
	<object class="MixerBusEffectChain" id="{3bb15dd7-2f60-4004-9f41-47465c0fe375}">
		<relationship name="effects">
			<destination>{e111ae01-ff33-474e-9068-25893055f3f5}</destination>
		</relationship>
	</object>
	<object class="MixerBusPanner" id="{3e908683-9dc0-48b8-a0f2-7113d4a4a294}" />
	<object class="MixerBusFader" id="{1f656114-c8eb-4194-a9f7-6b1428424cdc}" />
	<object class="MixerBusFader" id="{e111ae01-ff33-474e-9068-25893055f3f5}" />
</objects>
