<?xml version="1.0" encoding="UTF-8"?>
<objects serializationModel="Studio.02.02.00">
	<object class="AudioFile" id="{1620cb9d-f4ae-4d65-9102-9467d278eb2f}">
		<property name="assetPath">
			<value>music/pizzascape noise.wav</value>
		</property>
		<property name="frequencyInKHz">
			<value>48</value>
		</property>
		<property name="channelCount">
			<value>2</value>
		</property>
		<property name="length">
			<value>4.1012083333333331</value>
		</property>
		<relationship name="masterAssetFolder">
			<destination>{3ec376c7-9dab-4e28-9892-9388771afac6}</destination>
		</relationship>
	</object>
</objects>
