<?xml version="1.0" encoding="UTF-8"?>
<objects serializationModel="Studio.02.02.00">
	<object class="AudioFile" id="{4379894a-42ca-4cc7-b0ea-a3c280707e54}">
		<property name="assetPath">
			<value>sfx/johnending3.wav</value>
		</property>
		<property name="frequencyInKHz">
			<value>48</value>
		</property>
		<property name="channelCount">
			<value>2</value>
		</property>
		<property name="length">
			<value>1.5575416666666666</value>
		</property>
		<relationship name="masterAssetFolder">
			<destination>{3ec376c7-9dab-4e28-9892-9388771afac6}</destination>
		</relationship>
	</object>
</objects>
