<?xml version="1.0" encoding="UTF-8"?>
<objects serializationModel="Studio.02.02.00">
	<object class="AudioFile" id="{7c6f1431-f9a6-4881-b2df-05599fe34c06}">
		<property name="assetPath">
			<value>modded/sound/instinct/instinct7.wav</value>
		</property>
		<property name="frequencyInKHz">
			<value>48</value>
		</property>
		<property name="channelCount">
			<value>2</value>
		</property>
		<property name="length">
			<value>0.58860416666666671</value>
		</property>
		<relationship name="masterAssetFolder">
			<destination>{3ec376c7-9dab-4e28-9892-9388771afac6}</destination>
		</relationship>
	</object>
</objects>
