<?xml version="1.0" encoding="UTF-8"?>
<objects serializationModel="Studio.02.02.00">
	<object class="AudioFile" id="{d6b65719-06b2-4d55-80e6-e4fe2ae721c8}">
		<property name="assetPath">
			<value>sfx/fakepeppositive3.wav</value>
		</property>
		<property name="frequencyInKHz">
			<value>48</value>
		</property>
		<property name="channelCount">
			<value>2</value>
		</property>
		<property name="length">
			<value>2.8111875</value>
		</property>
		<relationship name="masterAssetFolder">
			<destination>{3ec376c7-9dab-4e28-9892-9388771afac6}</destination>
		</relationship>
	</object>
</objects>
